{
  "fatal":  {
    "SQL Injection": [
      "select\\s+.*\\s+from",
      "union\\s+select",
      "or\\s*1\\s*=\\s*1",
      "sleep\\s*\\(",
      "or\\s*['\"].*['\"]\\s*=\\s*['\"].*['\"]",
      "'\\s*or\\s*'",
      "\"\\s*or\\s*\"",
      "--",
      "#",
      "and\\s*1\\s*=\\s*1",
      "and\\s*['\"].*['\"]\\s*=\\s*['\"].*['\"]",
      "'\\s*=\\s*'",
      "information_schema",
      "union.*select",
      "order\\s+by\\s+\\d",
      "group\\s+by\\s+\\d",
      "having\\s+",
      "benchmark\\s*\\(",
      "waitfor\\s+delay",
      "load_file\\s*\\(",
      "into\\s+outfile",
      "into\\s+dumpfile"
    ],
    "XSS": [
      "<script",
      "javascript:",
      "onerror\\s*=",
      "onload\\s*=",
      "onclick\\s*=",
      "onmouseover\\s*=",
      "onfocus\\s*=",
      "onblur\\s*=",
      "alert\\s*\\(",
      "prompt\\s*\\(",
      "confirm\\s*\\(",
      "document\\.cookie",
      "document\\.location",
      "<img[^>]+onerror",
      "<svg[^>]+onload",
      "<iframe",
      "<object",
      "<embed",
      "<body[^>]+onload"
    ],
    "Command Injection": [
      ";\\s*cat",
      ";\\s*ls",
      ";\\s*id",
      ";\\s*whoami",
      ";\\s*pwd",
      "\\|\\s*cat",
      "\\|\\s*ls",
      "\\|\\s*id",
      "\\|\\s*whoami",
      "&&\\s*cat",
      "&&\\s*ls",
      "&&\\s*id",
      "&&\\s*whoami",
      "\\|\\|\\s*cat",
      "\\|\\|\\s*ls",
      "`[^`]+`",
      "\\$\\([^)]+\\)",
      "/etc/passwd",
      "/etc/shadow",
      "system\\s*\\(",
      "exec\\s*\\(",
      "shell_exec\\s*\\(",
      "passthru\\s*\\(",
      "eval\\s*\\(",
      "&\\s*dir",
      "&\\s*type",
      "\\|\\s*type"
    ],
    "CSRF": [
      "<input[^>]+csrf",
      "<meta[^>]+csrf"
    ],
    "File Inclusion": [
      "\\.\\.\\/",
      "\\.\\. \\\\",
      "/etc/passwd",
      "/etc/shadow",
      "/proc/self",
      "php://input",
      "php://filter",
      "file://",
      "data://",
      "expect://"
    ],
    "Brute Force": [
      "too many attempts",
      "login.*limit",
      "incorrect.*password"
    ]
  },
  "scoring":  [
    ["\\bselect\\b", 3],
    ["\\bunion\\b", 2],
    ["<script", 5],
    ["or\\s*['\"]", 5],
    ["system\\s*\\(", 4],
    ["exec\\s*\\(", 4],
    ["<iframe", 4],
    ["php://", 3]
  ]
}